.travis.yml
CHANGES.txt
MANIFEST.in
README.txt
bootstrap.py
buildout.cfg
setup.py
src/keas/__init__.py
src/keas.build.egg-info/PKG-INFO
src/keas.build.egg-info/SOURCES.txt
src/keas.build.egg-info/dependency_links.txt
src/keas.build.egg-info/entry_points.txt
src/keas.build.egg-info/namespace_packages.txt
src/keas.build.egg-info/not-zip-safe
src/keas.build.egg-info/requires.txt
src/keas.build.egg-info/top_level.txt
src/keas/build/__init__.py
src/keas/build/base.py
src/keas/build/build.py
src/keas/build/deploy.py
src/keas/build/index.txt
src/keas/build/install.py
src/keas/build/package.py
src/keas/build/sample/buildout.cfg
src/keas/build/sample/moo/Deploy.cfg
src/keas/build/sample/moo/Installers.cfg
src/keas/build/sample/moo/moo-Instance-Template.cfg
src/keas/build/sample/moo/moo-Project-Build.cfg
src/keas/build/sample/moo/moo-Release-Template.cfg